{"id": "13706", "subject": "Re: [EVP-ITC] EVP Maker", "author": "Frank Sumption", "timestamp": "2009-04-08T19:44:03Z", "full_text": "Raw audio is a term from EVPmaker, it&#39;s the bits of speech that thre\nentities use to form voices. Yiou record a short voice file to the computer,\nsaving it as a .wav, then EVPmaker takes that, breaks it up into chunks and\nplays it back while recording the results. Maybe I have the terms wrong, the\norignianl voice file might be call ed th eraw audio.\n\n In my boxes, I sweep the tuuing of a radio to crreate the raw audio, bits\nof human speech, music and noise that the entities re-mix into voices.\n\n F-S\n\nOn Wed, Apr 8, 2009 at 1:37 PM, lori bogren &lt;loribogren@...&gt; wrote:\n\n&gt;\n&gt;\n&gt; Frank~\n&gt;\n&gt; Thank you for the response, but I&#39;m a bit perplexed.  What do you mean it\n&gt; &quot;supplies the raw audio&quot;?\n&gt;\n&gt; ~Lori\n&gt;\n&gt;\n&gt; *&quot;My life is boring, my fantasies are a theme park.&quot;* --Anne Rice  *Responding\n&gt; to an interviewer who just did not get it.*\n&gt;\n&gt;\n&gt;\n&gt;\n&gt;\n&gt;\n&gt; ------------------------------\n&gt; To: EVP-ITC@yahoogroups.com\n&gt; From: purplealiengirl@...\n&gt; Date: Wed, 8 Apr 2009 12:27:53 -0600\n&gt; Subject: Re: [EVP-ITC] EVP Maker\n&gt;\n&gt;     EVPmaker supplies the raw audio the enities use to from their voices.\n&gt; Raw audio methods seem to produce clearer, and more consistent messages. The\n&gt; spritis and other entites seem to need bit of human speech and other noise\n&gt; to make their voices.\n&gt;\n&gt;  Frank-S\n&gt;\n&gt; On Wed, Apr 8, 2009 at 9:24 AM, lori bogren &lt;loribogren@...&gt;wrote:\n&gt;\n&gt;   Jon~\n&gt;\n&gt; What is the advantage of EVP Maker over using the built in recorder of\n&gt; Windows?\n&gt;\n&gt; ~Lori\n&gt;\n&gt;\n&gt; *&quot;My life is boring, my fantasies are a theme park.&quot;* --Anne Rice  *Responding\n&gt; to an interviewer who just did not get it.*\n&gt;\n&gt;\n&gt;\n&gt;\n&gt;\n&gt;\n&gt; ------------------------------\n&gt;\n&gt; To: EVP-ITC@yahoogroups.com\n&gt; From: jms480@...\n&gt; Date: Wed, 8 Apr 2009 06:49:01 -0700\n&gt; Subject: Re: [EVP-ITC] Some more from last month.\n&gt;\n&gt; Hi April,\n&gt;\n&gt; The lastest version of EVP maker allows you to capture EVP&#39;s directly to\n&gt; your laptop through a microphone attached to the Mic input on your laptop. I\n&gt; got mine from http://www.giveawayoftheday.com.  They give away a different\n&gt; software everyday.  They have a section for freeware that you can pickup any\n&gt; time.\n&gt;\n&gt;\n&gt; Regards,\n&gt; Jon in Texas\n&gt;\n&gt;\n&gt;\n&gt;  ------------------------------\n&gt; *From:* April Abercrombie &lt;april@abercrombieghostresearch.com&gt;\n&gt; *To:* EVP-ITC@yahoogroups.com\n&gt; *Sent:* Wednesday, April 8, 2009 8:35:32 AM\n&gt; *Subject:* Re: [EVP-ITC] Some more from last month.\n&gt;\n&gt;\n&gt; Wow! Those are pretty clear! And I have to say that I approve of the color.\n&gt; Purple is my favorite LOL!!!\n&gt;\n&gt; You know, I used to have on my computer little program that I downloaded\n&gt; called &quot;EVP Maker&quot;. I wonder if that is the same EVP maker you mentioned on\n&gt; this site. Unfortunately I lost it when I had to reformat my machine, and\n&gt; could not find the link to the original download. I believe I found the\n&gt; original link from the &quot;Shadowlands&quot; website, if I remember correctly.\n&gt;\n&gt; Besides that, this was YEARS ago, and I really did not understand how to\n&gt; use it, or even what it was for.\n&gt;\n&gt;\n&gt; ----- Original Message -----\n&gt; *From:* Frank Sumption &lt;purplealiengirl@...&gt;\n&gt; *To:* EVP-ITC@yahoogroups .com &lt;EVP-ITC@yahoogroups.com&gt;\n&gt; *Sent:* Tuesday, April 07, 2009 9:12 PM\n&gt; *Subject:* Re: [EVP-ITC] Some more from last month.\n&gt;\n&gt; Yeah, see http://purplealieng irl.tripod. com/&lt;http://purplealiengirl.tripod.com/&gt;\n&gt;\n&gt;\n&gt; On Tue, Apr 7, 2009 at 9:01 PM, April Abercrombie &lt;april@abercrombiegh\n&gt; ostresearch. com &lt;april@abercrombieghostresearch.com&gt;&gt; wrote:\n&gt;\n&gt;\n&gt; Realy?? Sweet!\n&gt;\n&gt;  .\n&gt;\n&gt;\n&gt; ------------------------------\n&gt; Windows Live™: Keep your life in sync. Check it out.&lt;http://windowslive.com/explore?ocid=TXT_TAGLM_WL_allup_1a_explore_042009&gt;\n&gt;\n&gt;\n&gt;\n&gt;\n&gt;\n&gt;\n&gt;\n&gt;\n&gt; ------------------------------\n&gt; Rediscover Hotmail®: Now available on your iPhone or BlackBerry Check it\n&gt; out.&lt;http://windowslive.com/RediscoverHotmail?ocid=TXT_TAGLM_WL_HM_Rediscover_Mobile1_042009&gt;\n&gt;\n&gt;  \n&gt;\n\nRaw audio is a e m om EVPmake , i 's he bi s o speech ha h e en i ies use o o m oices. Yiou eco d a sho   oice ile o he compu e , sa ing i as a .wa , hen EVPmake akes ha , b eaks i up in o chunks and plays i back while eco ding he esul s. Maybe I ha e he e ms w ong, he o ignianl oice ile migh be call ed h e aw audio. \n\n \n In my boxes, I sweep he uuing o a adio o c ea e he aw audio, bi s o human speech, music and noise ha he en i ies e-mix in o oices. \n \n F-S\nOn Wed, Ap 8, 2009 a 1:37 PM, lo i bog en lo ibog en@...> w o e:\n\n\n\n\n\nF ank~ Thank you o he esponse, bu I'm a bi pe plexed.  Wha do you mean i \"supplies he aw audio\"? \n ~Lo i\n\"My li e is bo ing, my an asies a e a heme pa k.\" \n--Anne Rice  Responding o an in e iewe who jus did no ge i .   \n\n\n\nTo: EVP-ITC@yahoog oups.comF om: pu plealiengi l@...Da e: Wed, 8 Ap 2009 12:27:53 -0600\nSubjec : Re: [EVP-ITC] EVP Make \n\n\n\n\n\n\n EVPmake supplies he aw audio he eni ies use o om hei oices. Raw audio me hods seem o p oduce clea e , and mo e consis en messages. The sp i is and o he en i es seem o need bi o human speech and o he noise o make hei oices. \n\n \n F ank-S\nOn Wed, Ap 8, 2009 a 9:24 AM, lo i bog en lo ibog en@...> w o e:\n\n\n\n\n\nJon~ Wha is he ad an age o EVP Make o e using he buil in eco de o Windows? ~Lo i\n\"My li e is bo ing, my an asies a e a heme pa k.\" \n--Anne Rice  Responding o an in e iewe who jus did no ge i .   \n\n\nTo: EVP-ITC@yahoog oups.comF om: jms480@yahoo.comDa e: Wed, 8 Ap 2009 06:49:01 -0700Subjec : Re: [EVP-ITC] Some mo e om las mon h.\n Hi Ap il,The las es e sion o EVP make allows you o cap u e EVP's di ec ly o you lap op h ough a mic ophone a ached o he Mic inpu on you lap op. I go mine om h p://www.gi eawayo heday.com.  They gi e away a di e en so wa e e e yday.  They ha e a sec ion o eewa e ha you can pickup any ime.\nRega ds,Jon in Texas \n\n\n\n\nF om: Ap il Abe c ombie ap il@abe c ombieghos esea ch.com>To: EVP-ITC@yahoog oups.com\nSen : Wednesday, Ap il 8, 2009 8:35:32 AMSubjec : Re: [EVP-ITC] Some mo e om las mon h.\n\nWow! Those a e p e y clea ! And I ha e o say ha I app o e o he colo . Pu ple is my a o i e LOL!!!\n \nYou know, I used o ha e on my compu e li le p og am ha I downloaded called \"EVP Make \". I wonde i ha is he same EVP make you men ioned on his si e. Un o una ely I los i when I had o e o ma my machine, and could no ind he link o he o iginal download. I belie e I ound he o iginal link om he \"Shadowlands\" websi e, i I emembe co ec ly.\n\n \nBesides ha , his was YEARS ago, and I eally did no unde s and how o use i , o e en wha i was o .\n \n\n----- O iginal Message ----- \nF om: F ank Sump ion \n\nTo: EVP-ITC@yahoog oups .com \n\nSen : Tuesday, Ap il 07, 2009 9:12 PM\nSubjec : Re: [EVP-ITC] Some mo e om las mon h.\n\nYeah, see h p://pu plealieng i l. ipod. com/ \nOn Tue, Ap 7, 2009 a 9:01 PM, Ap il Abe c ombie ap il@abe c ombiegh os esea ch. com> w o e:\n\n\n\n\n\n\nRealy?? Swee !\n\n. \n\n\nWindows Li e™: Keep you li e in sync. Check i ou . \n\n\n\n\n\n\nRedisco e Ho mail®: Now a ailable on you iPhone o BlackBe y Check i ou ."}