{"id": "16598", "subject": "files concerning the quake,", "author": "SnowfireL@aol.com", "timestamp": "2010-01-18T03:23:41Z", "full_text": "--part1_246db.48b9c40a.38852e3d_boundary\r\nContent-Type: multipart/alternative;\n\tboundary=&quot;part1_246db.48b9c40a.38852e3d_alt_boundary&quot;\r\n\r\n\r\n--part1_246db.48b9c40a.38852e3d_alt_boundary\r\nContent-Type: text/plain; charset=&quot;US-ASCII&quot;\r\nContent-Transfer-Encoding: 7bit\r\n\r\nGot these, one of my guides called David was  being paged to come back to \nHeaven to help with the emergency situation, seems  they are taking in over \n2,000 souls and it&#39;s been climbing.  They have  their hands full over there \nthat&#39;s for sure.  sf\n\r\n--part1_246db.48b9c40a.38852e3d_alt_boundary\r\nContent-Type: text/html; charset=&quot;US-ASCII&quot;\r\nContent-Transfer-Encoding: quoted-printable\r\n\r\n&lt;!DOCTYPE HTML PUBLIC &quot;-//W3C//DTD HTML 4.0 Transitional//EN&quot;&gt;\n&lt;HTML&gt;&lt;HEAD&gt;=\r\n\n&lt;META content=3D&quot;text/html; charset=3DUS-ASCII&quot; http-equiv=3DContent-Type&gt;=\r\n\n&lt;META name=3DGENERATOR content=3D&quot;MSHTML 8.00.6001.18854&quot;&gt;&lt;/HEAD&gt;\n&lt;BODY st=\r\nyle=3D&quot;FONT-FAMILY: Arial; COLOR: #000000; FONT-SIZE: 10pt&quot; id=3Drole_body =\r\n bottomMargin=3D7 leftMargin=3D7 rightMargin=3D7 topMargin=3D7&gt;&lt;FONT id=3Dr=\r\nole_document  color=3D#000000 size=3D2 face=3DArial&gt;\n&lt;DIV&gt;&lt;STRONG&gt;&lt;FONT col=\r\nor=3D#0000ff&gt;Got these, one of my guides called David was \nbeing paged to c=\r\nome back to Heaven to help with the emergency situation, seems \nthey are ta=\r\nking in over 2,000 souls and it&#39;s been climbing.&nbsp; They have \ntheir han=\r\nds full over there that&#39;s for sure. \nsf&lt;/FONT&gt;&lt;/STRONG&gt;&lt;/DIV&gt;&lt;/FONT&gt;&lt;/BODY&gt;=\r\n&lt;/HTML&gt;\n\r\n--part1_246db.48b9c40a.38852e3d_alt_boundary--\r\n\n\r\n--part1_246db.48b9c40a.38852e3d_boundary\r\nContent-Type: audio/x-wav; name=&quot;B_trouble master everywhere.wav&quot;\r\n\r\n[ Attachment content not displayed ]\r\n--part1_246db.48b9c40a.38852e3d_boundary\r\nContent-Type: audio/x-wav; name=&quot;H_hi john.wav&quot;\r\n\r\n[ Attachment content not displayed ]\r\n--part1_246db.48b9c40a.38852e3d_boundary\r\nContent-Type: audio/x-wav; name=&quot;M_emergency calling for you.wav&quot;\r\n\r\n[ Attachment content not displayed ]\r\n--part1_246db.48b9c40a.38852e3d_boundary\r\nContent-Type: audio/x-wav; name=&quot;M_unbelievable body of blood.wav&quot;\r\n\r\n[ Attachment content not displayed ]\r\n--part1_246db.48b9c40a.38852e3d_boundary\r\nContent-Type: audio/x-wav; name=&quot;S_emergency come help.wav&quot;\r\n\r\n[ Attachment content not displayed ]\r\n--part1_246db.48b9c40a.38852e3d_boundary--"}