{"id": "2933", "subject": "RE: [EVP-ITC] Sound Soap 2 Sweep", "author": "RetroCom", "timestamp": "2007-11-13T23:35:58Z", "full_text": "----__Part.20071113153558.D9F6FA03\r\nContent-Type: text/plain; charset=&quot;UTF-8&quot;\r\n\r\nThanks Frank, speaking of validation.\n&quot;We go on living&quot;\n\n--- franks-boxes@... wrote:\n\nFrom: Frank Sumption &lt;franks-boxes@...&gt;\nTo: &lt;evp-itc@yahoogroups.com&gt;\nSubject: RE: [EVP-ITC] Sound Soap 2 Sweep\nDate: Tue, 13 Nov 2007 07:38:00 -0700\n\n\n Way cool, and pretty clear. Moon said both Tesla and Edison were working on machines. There&#39;s people out there beating up Chris, but he keeps getting validated! That&#39;s why I had to go back to work wiht him. I&#39;m, an old crank, but I won&#39;t let ego crap get inthe way---and I trust my intuition. \n \n There&#39;s some that believe life continues on thre other side pretty much as we are here, and &quot;they&quot; are as physical there, and we are here. Not the whisps of energy the paranormal experts would have us believe. \n \n Frank\n\n\nTo: EVP-ITC@yahoogroups.comFrom: vfp19968@...: Tue, 13 Nov 2007 03:37:50 -0800Subject: [EVP-ITC] Sound Soap 2 Sweep\n\n\n\n\nTrying a new technique on th computer using editing software called Sound Soap 2. I discovered a way to do a manual forward/reverse sweep of any audio file. Here is an example from last night. The effect is somewhat like EVP maker and exibits some layering.&quot;I&#39;m down in Chicago on Tesla&#39;s device alive!...Edison, should never meddle&quot;Dave \n\n\n\n\n\n\n_________________________________________________________________\nPeek-a-boo FREE Tricks & Treats for You!\nhttp://www.reallivemoms.com?ocid=TXT_TAGHM&loc=us\n\n\r\n----__Part.20071113153558.D9F6FA03\r\nContent-Type: audio/mpeg; name=&quot;111207wegoonliving (3).mp3&quot;\r\nContent-Disposition: attachment; filename=&quot;111207wegoonliving (3).mp3&quot;\r\n\r\n[ Attachment content not displayed ]\r\n----__Part.20071113153558.D9F6FA03--"}