{"id": "8822", "subject": "Re: Arthur&#39;s take on portals...", "author": "itcdeadpeople", "timestamp": "2008-04-02T21:51:08Z", "full_text": "Thanks Stefan.  I heard that too!  Sometimes I miss things during the session because I&#39;m \ntalking over him.  I think there&#39;s a learning curve on both sides.  \n\nMargaret\n\n--- In EVP-ITC@yahoogroups.com, Stefan Bion &lt;yahoogroups@...&gt; wrote:\n&gt;\n&gt; Hi Margaret,\n&gt; \n&gt; &gt; I&#39;m gonna listen again. Thanks Arthur.\n&gt; \n&gt; Between these two sentences, I can hear very clearly &quot;Love you&quot;:\n&gt; \n&gt; http://groups.yahoo.com/group/EVP-ITC/files/Stefan/20080402_Margaret_LoveYou.mp3\n&gt; \n&gt; Stefan\n&gt;"}